<?xml version='1.0' encoding='UTF-8'?>
<?artifactRepository version='1.1.0'?>
<repository name='Update Site' type='org.eclipse.equinox.p2.artifact.repository.simpleRepository' version='1.0.0'>
  <properties size='2'>
    <property name='p2.timestamp' value='1721231370757'/>
    <property name='p2.compressed' value='true'/>
  </properties>
  <mappings size='3'>
    <rule filter='(&amp; (classifier=osgi.bundle))' output='${repoUrl}/plugins/${id}_${version}.jar'/>
    <rule filter='(&amp; (classifier=binary))' output='${repoUrl}/binary/${id}_${version}'/>
    <rule filter='(&amp; (classifier=org.eclipse.update.feature))' output='${repoUrl}/features/${id}_${version}.jar'/>
  </mappings>
  <artifacts size='3'>
    <artifact classifier='org.eclipse.update.feature' id='org.eclipse.core.pki.feature' version='1.0.5.202407171149'>
      <properties size='2'>
        <property name='download.contentType' value='application/zip'/>
        <property name='download.size' value='479'/>
      </properties>
    </artifact>
    <artifact classifier='osgi.bundle' id='org.eclipse.core.pki' version='1.0.2.202407221231'>
      <properties size='4'>
        <property name='artifact.size' value='81276'/>
        <property name='download.size' value='81276'/>
        <property name='download.checksum.sha-512' value='426769f74543f6c54966eb89f646969461f108a8b8d3d001edb5ba80d634ac00f733e807adc644927d9394e9207d1883800b5dc6449668ba4dca3f8b643eb534'/>
        <property name='download.checksum.sha-256' value='8ed241149354a6ac26e785f5774714d8dc0e0d75078e5c3e91abbed7d66f35ef'/>
      </properties>
    </artifact>
    <artifact classifier='osgi.bundle' id='org.eclipse.ui.pki' version='1.0.0.202407221231'>
      <properties size='4'>
        <property name='artifact.size' value='122708'/>
        <property name='download.size' value='122708'/>
        <property name='download.checksum.sha-512' value='b06a0068b3ec0fb6d8e770a1a236766ba89f882279530935f130f2c989380647ac776575c5f16a95a3dce83d6ba2e6025c1ab54e54a3ebe8d25e7579c6049ba0'/>
        <property name='download.checksum.sha-256' value='b10d48cf7d01ff17fa47a4afb737d55cc3aa1936a5c418fb54d6b29850a5e162'/>
      </properties>
    </artifact>
  </artifacts>
</repository>
